src/rlm_mcp_server.py
massive_context_mcp-3.0.1.dist-info/METADATA
massive_context_mcp-3.0.1.dist-info/WHEEL
massive_context_mcp-3.0.1.dist-info/entry_points.txt
massive_context_mcp-3.0.1.dist-info/licenses/LICENSE
massive_context_mcp-3.0.1.dist-info/RECORD
