Metadata-Version: 2.4
Name: massive-context-mcp
Version: 3.0.1
Summary: Handle 10M+ token contexts with chunking, sub-queries, and local Ollama inference
Project-URL: Homepage, https://github.com/egoughnour/massive-context-mcp
Project-URL: Repository, https://github.com/egoughnour/massive-context-mcp
Project-URL: Issues, https://github.com/egoughnour/massive-context-mcp/issues
Author-email: Erik Goughnour <e.goughnour@gmail.com>
License: MIT
License-File: LICENSE
Keywords: chunking,claude,llm,local-inference,massive-context,mcp,model-context-protocol,ollama
Classifier: Development Status :: 4 - Beta
Classifier: Intended Audience :: Developers
Classifier: License :: OSI Approved :: MIT License
Classifier: Programming Language :: Python :: 3
Classifier: Programming Language :: Python :: 3.10
Classifier: Programming Language :: Python :: 3.11
Classifier: Programming Language :: Python :: 3.12
Classifier: Programming Language :: Python :: 3.13
Classifier: Topic :: Scientific/Engineering :: Artificial Intelligence
Requires-Python: >=3.10
Requires-Dist: fastmcp>=2.0.0
Requires-Dist: httpx>=0.27.0
Provides-Extra: claude
Requires-Dist: claude-agent-sdk>=0.1.0; extra == 'claude'
Provides-Extra: dev
Requires-Dist: pytest-asyncio>=0.24.0; extra == 'dev'
Requires-Dist: pytest-cov>=4.0.0; extra == 'dev'
Requires-Dist: pytest>=8.0.0; extra == 'dev'
Requires-Dist: ruff>=0.1.0; extra == 'dev'
Provides-Extra: firewall
Requires-Dist: code-firewall-mcp>=0.1.0; extra == 'firewall'
